scanfs/__init__.py
scanfs/fsscanner.py
scanfs/fsscannerex.py
scanfs-0.0.6.dist-info/LICENSE.txt
scanfs-0.0.6.dist-info/METADATA
scanfs-0.0.6.dist-info/WHEEL
scanfs-0.0.6.dist-info/top_level.txt
scanfs-0.0.6.dist-info/RECORD
