Metadata-Version: 2.1
Name: scanfs
Version: 0.0.6
Summary: File system scanner in Python
Home-page: https://github.com/cpuinfo/scanfs
Author: CPU Info
Author-email: cpuinfo10@gmail.com
License: UNKNOWN
Platform: UNKNOWN
Classifier: Programming Language :: Python :: 3
Classifier: Operating System :: POSIX
Classifier: Intended Audience :: Developers
Classifier: License :: OSI Approved :: MIT License
Classifier: Topic :: Software Development :: Libraries :: Python Modules
License-File: LICENSE.txt
